dss_wdc_client/__init__py
dss_wdc_client/client.py
dss_wdc_client-0.9.1.dist-info/METADATA
dss_wdc_client-0.9.1.dist-info/WHEEL
dss_wdc_client-0.9.1.dist-info/RECORD
