Metadata-Version: 2.3
Name: dss.wdc_client
Version: 0.9.1
Summary: A small client for the WDC-Rest-API.
Author: Tino Schöllhorn
Author-email: t.schoellhorn@uni-mannheim.de
Requires-Python: >=3.10
Classifier: Programming Language :: Python :: 3
Classifier: Programming Language :: Python :: 3.10
Classifier: Programming Language :: Python :: 3.11
Classifier: Programming Language :: Python :: 3.12
Classifier: Programming Language :: Python :: 3.13
Provides-Extra: docs
Requires-Dist: Sphinx (==7.4.7) ; extra == "docs"
Requires-Dist: networkx (>=3.0)
Requires-Dist: pandas[excel, plot] (>=2.2,<3.0)
Requires-Dist: python-dotenv (>=1.1.0)
Requires-Dist: requests (>=2.3)
Requires-Dist: sphinx-rtd-theme (==3.0.2) ; extra == "docs"
Requires-Dist: sphinxcontrib-napoleon (==0.7) ; extra == "docs"
Project-URL: Documentation, https://dss-wdc.wiso.uni-hamburg.de/dss_wdc_client_docs/html/index.html
Project-URL: Homepage, https://dss-wdc.wiso.uni-hamburg.de/
